{
    "name": "Licence",
    "fields": [
        {
            "fieldName": "titre",
            "fieldType": "String"
        },
        {
            "fieldName": "prix",
            "fieldType": "Integer"
        }
    ],
    "relationships": [
        {
            "relationshipName": "thirdparty",
            "otherEntityName": "thirdparty",
            "relationshipType": "many-to-one",
            "otherEntityField": "id"
        },
        {
            "relationshipType": "one-to-one",
            "otherEntityName": "userApp",
            "otherEntityRelationshipName": "licence",
            "relationshipName": "userLicence",
            "otherEntityField": "id",
            "ownerSide": true
        }
    ],
    "changelogDate": "20190411114955",
    "entityTableName": "licence",
    "dto": "no",
    "pagination": "no",
    "service": "no",
    "jpaMetamodelFiltering": false,
    "fluentMethods": true,
    "clientRootFolder": "",
    "applications": "*"
}